Point.cpython-39-darwin.so
__init__.cpython-39-darwin.so
PyGeom3D/Point.cpython-39-darwin.so
PyGeom3D/__init__.cpython-39-darwin.so
PyGeom3D-0.0.2.dist-info/METADATA
PyGeom3D-0.0.2.dist-info/WHEEL
PyGeom3D-0.0.2.dist-info/top_level.txt
PyGeom3D-0.0.2.dist-info/RECORD
